bluesky/__init__.py
bluesky/__main__.py
bluesky/_version.py
bluesky/bundlers.py
bluesky/cntx.py
bluesky/consolidators.py
bluesky/examples.py
bluesky/interactive.py
bluesky/log.py
bluesky/magics.py
bluesky/plan_patterns.py
bluesky/plan_stubs.py
bluesky/plan_tools.py
bluesky/plans.py
bluesky/preprocessors.py
bluesky/protocols.py
bluesky/py.typed
bluesky/run_engine.py
bluesky/simulators.py
bluesky/suspenders.py
bluesky/tracing.py
bluesky/_vendor/README.rst
bluesky/_vendor/__init__.py
bluesky/_vendor/six.LICENSE
bluesky/_vendor/six.py
bluesky/_vendor/six.pyi
bluesky/_vendor/super_state_machine.pyi
bluesky/_vendor/vendor.txt
bluesky/_vendor/super_state_machine/LICENSE
bluesky/_vendor/super_state_machine/__init__.py
bluesky/_vendor/super_state_machine/errors.py
bluesky/_vendor/super_state_machine/extras.py
bluesky/_vendor/super_state_machine/machines.py
bluesky/_vendor/super_state_machine/utils.py
bluesky/callbacks/__init__.py
bluesky/callbacks/best_effort.py
bluesky/callbacks/broker.py
bluesky/callbacks/buffer.py
bluesky/callbacks/core.py
bluesky/callbacks/fitting.py
bluesky/callbacks/json_writer.py
bluesky/callbacks/mpl_plotting.py
bluesky/callbacks/olog.py
bluesky/callbacks/stream.py
bluesky/callbacks/tiled_writer.py
bluesky/callbacks/zmq.py
bluesky/commandline/__init__.py
bluesky/commandline/zmq_proxy.py
bluesky/tests/__init__.py
bluesky/tests/conftest.py
bluesky/tests/test_bec.py
bluesky/tests/test_buffering.py
bluesky/tests/test_callbacks.py
bluesky/tests/test_cli.py
bluesky/tests/test_consolidators.py
bluesky/tests/test_devices.py
bluesky/tests/test_documents.py
bluesky/tests/test_event_loop_funcs.py
bluesky/tests/test_examples.py
bluesky/tests/test_external_assets_and_paging.py
bluesky/tests/test_flyer.py
bluesky/tests/test_generators.py
bluesky/tests/test_json_writer.py
bluesky/tests/test_legacy_plans.py
bluesky/tests/test_logging.py
bluesky/tests/test_magics.py
bluesky/tests/test_metadata.py
bluesky/tests/test_multi_runs.py
bluesky/tests/test_new_examples.py
bluesky-1.14.6.dist-info/licenses/LICENSE
bluesky-1.14.6.dist-info/licenses/LICENSE_README
bluesky-1.14.6.dist-info/METADATA
bluesky-1.14.6.dist-info/WHEEL
bluesky-1.14.6.dist-info/entry_points.txt
bluesky-1.14.6.dist-info/top_level.txt
bluesky-1.14.6.dist-info/RECORD
