Metadata-Version: 2.4
Name: bluesky
Version: 1.14.6
Summary: Experiment specification & orchestration.
Author: danielballan
License: BSD 3-Clause License
Project-URL: GitHub, https://github.com/bluesky/bluesky
Classifier: Development Status :: 3 - Alpha
Classifier: License :: OSI Approved :: Apache Software License
Classifier: Programming Language :: Python :: 3.9
Classifier: Programming Language :: Python :: 3.10
Classifier: Programming Language :: Python :: 3.11
Classifier: Programming Language :: Python :: 3.12
Requires-Python: >=3.9
License-File: LICENSE
License-File: LICENSE_README
Requires-Dist: cycler
Requires-Dist: event-model>=1.23.1
Requires-Dist: historydict
Requires-Dist: msgpack
Requires-Dist: msgpack-numpy
Requires-Dist: numpy
Requires-Dist: opentelemetry-api
Requires-Dist: toolz
Requires-Dist: tqdm>=4.44
Requires-Dist: typing-extensions>=4.10.0
Provides-Extra: dev
Requires-Dist: attrs; extra == "dev"
Requires-Dist: cloudpickle; extra == "dev"
Requires-Dist: copier; extra == "dev"
Requires-Dist: coverage; extra == "dev"
Requires-Dist: databroker; extra == "dev"
Requires-Dist: doct; extra == "dev"
Requires-Dist: doctr; extra == "dev"
Requires-Dist: flake8; extra == "dev"
Requires-Dist: ipython; extra == "dev"
Requires-Dist: ipywidgets; extra == "dev"
Requires-Dist: jinja2; extra == "dev"
Requires-Dist: lmfit; extra == "dev"
Requires-Dist: matplotlib>=3.5.0; extra == "dev"
Requires-Dist: mongoquery; extra == "dev"
Requires-Dist: multiprocess; extra == "dev"
Requires-Dist: mypy; extra == "dev"
Requires-Dist: myst-parser; extra == "dev"
Requires-Dist: networkx; extra == "dev"
Requires-Dist: numpydoc; extra == "dev"
Requires-Dist: ophyd; extra == "dev"
Requires-Dist: orjson; extra == "dev"
Requires-Dist: packaging; extra == "dev"
Requires-Dist: pandas; extra == "dev"
Requires-Dist: pickleshare; extra == "dev"
Requires-Dist: pipdeptree; extra == "dev"
Requires-Dist: pre-commit; extra == "dev"
Requires-Dist: pydata-sphinx-theme>=0.12; extra == "dev"
Requires-Dist: pyepics<=3.5.2; python_version < "3.9" and extra == "dev"
Requires-Dist: pyepics; python_version >= "3.9" and extra == "dev"
Requires-Dist: pyqt5; extra == "dev"
Requires-Dist: pytest; extra == "dev"
Requires-Dist: pytest-cov; extra == "dev"
Requires-Dist: pytest-faulthandler; extra == "dev"
Requires-Dist: pyyaml; extra == "dev"
Requires-Dist: pyzmq; extra == "dev"
Requires-Dist: requests; extra == "dev"
Requires-Dist: ruff; extra == "dev"
Requires-Dist: scikit-image; extra == "dev"
Requires-Dist: scipy; extra == "dev"
Requires-Dist: sphinx<7.3; extra == "dev"
Requires-Dist: sphinx-autobuild; extra == "dev"
Requires-Dist: sphinx-copybutton; extra == "dev"
Requires-Dist: sphinx-design; extra == "dev"
Requires-Dist: sphinxcontrib-mermaid; extra == "dev"
Requires-Dist: sphinx_rtd_theme; extra == "dev"
Requires-Dist: streamz; extra == "dev"
Requires-Dist: suitcase-jsonl; extra == "dev"
Requires-Dist: suitcase-mongo; extra == "dev"
Requires-Dist: suitcase-msgpack; extra == "dev"
Requires-Dist: tifffile; extra == "dev"
Requires-Dist: tox-direct; extra == "dev"
Requires-Dist: types-mock; extra == "dev"
Requires-Dist: tiled[all]; extra == "dev"
Requires-Dist: vendoring; extra == "dev"
Requires-Dist: zict; extra == "dev"
Provides-Extra: ipython
Requires-Dist: ipython; extra == "ipython"
Provides-Extra: zmq
Requires-Dist: pyzmq; extra == "zmq"
Provides-Extra: common
Requires-Dist: ophyd; extra == "common"
Requires-Dist: databroker; extra == "common"
Provides-Extra: tools
Requires-Dist: doct; extra == "tools"
Requires-Dist: lmfit; extra == "tools"
Requires-Dist: tifffile; extra == "tools"
Requires-Dist: historydict; extra == "tools"
Provides-Extra: streamz
Requires-Dist: streamz; extra == "streamz"
Provides-Extra: plotting
Requires-Dist: matplotlib; extra == "plotting"
Provides-Extra: cmd
Requires-Dist: colorama; extra == "cmd"
Provides-Extra: olog
Requires-Dist: jinja2; extra == "olog"
Provides-Extra: old-persistentdict
Requires-Dist: zict<3; extra == "old-persistentdict"
Provides-Extra: all
Requires-Dist: bluesky[cmd,common,dev,ipython,olog,plotting,streamz,tools,zmq]; extra == "all"
Dynamic: license-file
